promptmin/__init__.py
promptmin/cli.py
promptmin/minimize.py
promptmin-1.0.2.dist-info/licenses/LICENSE
promptmin-1.0.2.dist-info/METADATA
promptmin-1.0.2.dist-info/WHEEL
promptmin-1.0.2.dist-info/entry_points.txt
promptmin-1.0.2.dist-info/top_level.txt
promptmin-1.0.2.dist-info/RECORD
