Metadata-Version: 2.4
Name: promptmin
Version: 1.0.2
Summary: Prompt minimizer for LLM evals — shrink prompts to minimal failing inputs using delta debugging
License-Expression: MIT
Project-URL: Homepage, https://github.com/10fra/promptmin
Project-URL: Repository, https://github.com/10fra/promptmin
Project-URL: Issues, https://github.com/10fra/promptmin/issues
Keywords: prompt,llm,eval,ddmin,delta-debugging,debugging,testing
Classifier: Development Status :: 4 - Beta
Classifier: Intended Audience :: Developers
Classifier: Topic :: Software Development :: Testing
Classifier: Topic :: Scientific/Engineering :: Artificial Intelligence
Classifier: Programming Language :: Python :: 3
Classifier: Programming Language :: Python :: 3.9
Classifier: Programming Language :: Python :: 3.10
Classifier: Programming Language :: Python :: 3.11
Classifier: Programming Language :: Python :: 3.12
Classifier: Operating System :: OS Independent
Requires-Python: >=3.9
License-File: LICENSE
Dynamic: license-file
